nubix_ai/__init__.py
nubix_ai-1.0.0.dist-info/METADATA
nubix_ai-1.0.0.dist-info/WHEEL
nubix_ai-1.0.0.dist-info/RECORD
